probkit/__init__.py
probkit/curves.py
probkit/probability.py
probkit/sampling.py
probkit/utils.py
probkit-0.2.1.dist-info/licenses/LICENSE
probkit-0.2.1.dist-info/METADATA
probkit-0.2.1.dist-info/WHEEL
probkit-0.2.1.dist-info/top_level.txt
probkit-0.2.1.dist-info/RECORD
