Metadata-Version: 2.4
Name: probkit
Version: 0.2.1
Summary: Toolkit for modifying probabilities and shaping curves.
Author-email: Taylor Vance <mirrors.cities0w@icloud.com>
License-Expression: MIT
Project-URL: Homepage, https://github.com/taylorvance/probkit
Project-URL: Repository, https://github.com/taylorvance/probkit
Project-URL: Issues, https://github.com/taylorvance/probkit/issues
Keywords: probability,curves,sigmoid,mathematics,simulation,statistics
Requires-Python: >=3.9
License-File: LICENSE
Dynamic: license-file
